tf_compactprogbar/__init__.py
tf_compactprogbar/tf_compactprogbar.py
tf_compactprogbar-1.0.2.dist-info/LICENSE
tf_compactprogbar-1.0.2.dist-info/METADATA
tf_compactprogbar-1.0.2.dist-info/WHEEL
tf_compactprogbar-1.0.2.dist-info/top_level.txt
tf_compactprogbar-1.0.2.dist-info/RECORD
