Metadata-Version: 2.1
Name: tf_compactprogbar
Version: 1.0.2
Summary: A simple and compact one-line progress bar for TensorFlow 2 Keras.
Author: Adam Wu
Author-email: adamwu1@outlook.com
License: MIT License
Project-URL: homepage, https://github.com/adamvvu/tf_compactprogbar
Project-URL: documentation, https://github.com/adamvvu/tf_compactprog_bar
Project-URL: repository, https://github.com/adamvvu/tf_compactprogbar
Keywords: tensorflow,progress bar,callbacks,deep learning
Classifier: Intended Audience :: Science/Research
Classifier: Topic :: Scientific/Engineering :: Artificial Intelligence
Classifier: Topic :: Scientific/Engineering :: Information Analysis
Classifier: Programming Language :: Python
Classifier: Operating System :: OS Independent
Classifier: License :: OSI Approved :: MIT License
Requires-Python: >=3.7
License-File: LICENSE
Requires-Dist: tensorflow
Requires-Dist: tqdm
Requires-Dist: ipywidgets
